setup.py
flag_0o3641112/__init__.py
flag_0o3641112/flag_0o3641112.py
flag_0o3641112.egg-info/PKG-INFO
flag_0o3641112.egg-info/SOURCES.txt
flag_0o3641112.egg-info/dependency_links.txt
flag_0o3641112.egg-info/top_level.txt