Metadata-Version: 2.1
Name: flag-0o3641112
Version: 1.0
Summary: desc
Home-page: UNKNOWN
Author: OsOmE1
Author-email: 
License: MIT
Download-URL: https://pypi.org/project/flag_0o3641112/
Keywords: simple_codecs,Encryption,Encoding
Platform: UNKNOWN
